webcat_agent/__init__.py
webcat_agent/__main__.py
webcat_agent-1.0.12.dist-info/METADATA
webcat_agent-1.0.12.dist-info/WHEEL
webcat_agent-1.0.12.dist-info/entry_points.txt
webcat_agent-1.0.12.dist-info/RECORD
