Metadata-Version: 2.3
Name: webcat-agent
Version: 1.0.12
Summary: WebCat Agent
Project-URL: homepage, https://github.com/webcatfi/webcatfi
Project-URL: repository, https://github.com/webcatfi/webcatfi
Author-email: Kenneth Falck <kennu@clouden.net>
License: MIT
Provides-Extra: ci
Provides-Extra: tests
Requires-Dist: pytest; extra == 'tests'
